vocball/__init__.py
vocball/editor.py
vocball/game.py
vocball/list.py
vocball/settings.py
vocball/vocball.py
vocball/simpleaudio/LICENSE.txt
vocball/simpleaudio/README.rst
vocball/simpleaudio/__init__.py
vocball/simpleaudio/_simpleaudio.so
vocball/simpleaudio/simpleaudio.py
vocball-1.1.0.data/data/share/applications/de.RomaAeterna.VocBall.desktop
vocball-1.1.0.data/data/share/icons/hicolor/16x16/apps/de.RomaAeterna.VocBall.png
vocball-1.1.0.data/data/share/icons/hicolor/22x22/apps/de.RomaAeterna.VocBall.png
vocball-1.1.0.data/data/share/icons/hicolor/24x24/apps/de.RomaAeterna.VocBall.png
vocball-1.1.0.data/data/share/icons/hicolor/256x256/apps/de.RomaAeterna.VocBall.png
vocball-1.1.0.data/data/share/icons/hicolor/32x32/apps/de.RomaAeterna.VocBall.png
vocball-1.1.0.data/data/share/icons/hicolor/48x48/apps/de.RomaAeterna.VocBall.png
vocball-1.1.0.data/data/share/icons/hicolor/512x512/apps/de.RomaAeterna.VocBall.png
vocball-1.1.0.data/data/share/locale/C/LC_MESSAGES/vocball.mo
vocball-1.1.0.data/data/share/locale/de/LC_MESSAGES/vocball.mo
vocball-1.1.0.data/data/share/locale/en_GB/LC_MESSAGES/vocball.mo
vocball-1.1.0.data/data/share/locale/va/LC_MESSAGES/vocball.mo
vocball-1.1.0.data/data/share/vocball/pixmaps/arrowdownleft_75x75.png
vocball-1.1.0.data/data/share/vocball/pixmaps/arrowdownright_75x75.png
vocball-1.1.0.data/data/share/vocball/pixmaps/arrowupleft_75x75.png
vocball-1.1.0.data/data/share/vocball/pixmaps/arrowupright_75x75.png
vocball-1.1.0.data/data/share/vocball/pixmaps/football_100x100.png
vocball-1.1.0.data/data/share/vocball/pixmaps/footballfield_1382x838.svg
vocball-1.1.0.data/data/share/vocball/pixmaps/logo_128x128.png
vocball-1.1.0.data/data/share/vocball/pixmaps/score0_30x50_dark.png
vocball-1.1.0.data/data/share/vocball/pixmaps/score0_30x50_light.png
vocball-1.1.0.data/data/share/vocball/pixmaps/score1_30x50_dark.png
vocball-1.1.0.data/data/share/vocball/pixmaps/score1_30x50_light.png
vocball-1.1.0.dist-info/DESCRIPTION.rst
vocball-1.1.0.dist-info/METADATA
vocball-1.1.0.dist-info/RECORD
vocball-1.1.0.dist-info/WHEEL
vocball-1.1.0.dist-info/metadata.json
vocball-1.1.0.dist-info/top_level.txt
