Metadata-Version: 2.0
Name: vocball
Version: 1.1.0
Summary: Play vocabulary football in class
Home-page: https://gitlab.com/romaaeterna/vocball
Author: Thomas Dähnrich
License: GPL-3+
Keywords: education,game
Platform: UNKNOWN
Classifier: Development Status :: 5 - Production/Stable
Classifier: Environment :: X11 Applications :: GTK
Classifier: License :: OSI Approved :: GNU General Public License v3 or later (GPLv3+)
Classifier: Operating System :: POSIX :: Linux
Classifier: Programming Language :: Python :: 3 :: Only
Classifier: Topic :: Desktop Environment :: Gnome
Classifier: Topic :: Education
Classifier: Topic :: Games/Entertainment
Requires-Python: >=3.3
